{
"type": "FeatureCollection",
"name": "Auckland_Council_Imagery_2022_2024 Imagery Centres",
"crs": { "type": "name", "properties": { "name": "urn:ogc:def:crs:OGC:1.3:CRS84" } },
"features": [
{ "type": "Feature", "properties": { "Project": "PGRM3077", "Company_Name": "Auckland Council", "SN_No": "SN14259", "Description": "Auckland Region - 2022-25 4732 ft Flying & Orthos", "OrthoGSD_m": 0.075, "PointDensity_(points/m2)": null, "Area": 2052.0938460067009, "Percentage_Coverage": null }, "geometry": { "type": "Point", "coordinates": [ 174.841413113177225, -36.874199889275829 ] } }
]
}
